mugennobot/lang.py
mugennobot/model/db.py
mugennobot/mugenbot.py
mugennobot/utils/consts.py
mugennobot-0.1.5.dist-info/METADATA
mugennobot-0.1.5.dist-info/WHEEL
mugennobot-0.1.5.dist-info/RECORD
