Metadata-Version: 2.3
Name: mugennobot
Version: 0.1.5
Summary: Bot for the Mugen Project
License: AGPLv3
Author: Kyamel
Author-email: lcamelo200@gmail.com
Requires-Python: >=3.12
Classifier: License :: Other/Proprietary License
Classifier: Programming Language :: Python :: 3
Classifier: Programming Language :: Python :: 3.12
Classifier: Programming Language :: Python :: 3.13
Requires-Dist: aiosqlite (>=0.21.0,<0.22.0)
Requires-Dist: discord (>=2.3.2,<3.0.0)
Requires-Dist: dotenv (>=0.9.9,<0.10.0)
Requires-Dist: mugennoscraper (>=0.1.6,<0.2.0)
